py_qoi/__init__.py
py_qoi/qoi.py
py_qoi_encoder-0.1.2.dist-info/LICENSE
py_qoi_encoder-0.1.2.dist-info/METADATA
py_qoi_encoder-0.1.2.dist-info/WHEEL
py_qoi_encoder-0.1.2.dist-info/top_level.txt
py_qoi_encoder-0.1.2.dist-info/RECORD
