Metadata-Version: 2.2
Name: py-qoi-encoder
Version: 0.1.2
Summary: A Python QOI encoder/decoder.
Author-email: Abdulrahman Alsalman <abdulrahmanalsalman13@gmail.com>
License: MIT License
Project-URL: Source Code, https://github.com/Apeto13/py-qoi
Classifier: Programming Language :: Python :: 3
Requires-Python: >=3.7
License-File: LICENSE
